finance_ml/__init__.py
finance_ml/dataprep_ml.py
finance_ml-0.0.4.dist-info/LICENSE
finance_ml-0.0.4.dist-info/METADATA
finance_ml-0.0.4.dist-info/WHEEL
finance_ml-0.0.4.dist-info/top_level.txt
finance_ml-0.0.4.dist-info/RECORD
